[{"trade_id":"TAA-2025-LiberationDay_LongUS","long_ticker":"USEQ_US","short_ticker":"CASH_USD","entry_date":"2025-05-01","exit_date":"2025-11-15","long_total_return":0.2176,"short_total_return":0.0238,"spread_total_return":0.1893,"vol":0.1149,"sharpe":2.7357,"max_drawdown":-0.0299,"days_held":142},{"trade_id":"TAA-2025-LongBunds","long_ticker":"DEBO10","short_ticker":"CASH_EUR","entry_date":"2024-09-15","exit_date":"2025-11-15","long_total_return":0.0079,"short_total_return":0.0534,"spread_total_return":-0.0432,"vol":0.0526,"sharpe":-0.6673,"max_drawdown":-0.071,"days_held":305},{"trade_id":"TAA-2025-LongGilts","long_ticker":"UKBO10","short_ticker":"CASH_GBP","entry_date":"2024-09-01","long_total_return":0.0229,"short_total_return":0.0601,"spread_total_return":-0.0351,"vol":0.057,"sharpe":-0.4305,"max_drawdown":-0.0858,"days_held":344}]
